.long-description.html
CHANGES.txt
MANIFEST.in
README.txt
setup.py
cs/__init__.py
cs.video.egg-info/PKG-INFO
cs.video.egg-info/SOURCES.txt
cs.video.egg-info/dependency_links.txt
cs.video.egg-info/entry_points.txt
cs.video.egg-info/namespace_packages.txt
cs.video.egg-info/not-zip-safe
cs.video.egg-info/requires.txt
cs.video.egg-info/top_level.txt
cs/video/__init__.py
cs/video/config.py
cs/video/configure.zcml
cs/video/interfaces.py
cs/video/profiles.zcml
cs/video/rebuild_i18n.sh
cs/video/skins.zcml
cs/video/tests.py
cs/video/Extensions/Install.py
cs/video/Extensions/__init__.py
cs/video/browser/__init__.py
cs/video/browser/activate.py
cs/video/browser/configure.zcml
cs/video/browser/videos.py
cs/video/content/__init__.py
cs/video/content/configure.zcml
cs/video/content/video.py
cs/video/locales/cs.video-manual.pot
cs/video/locales/cs.video.pot
cs/video/locales/en/LC_MESSAGES/cs.video.mo
cs/video/locales/en/LC_MESSAGES/cs.video.po
cs/video/locales/es/LC_MESSAGES/cs.video.mo
cs/video/locales/es/LC_MESSAGES/cs.video.po
cs/video/locales/eu/LC_MESSAGES/cs.video.mo
cs/video/locales/eu/LC_MESSAGES/cs.video.po
cs/video/profiles/default/actions.xml
cs/video/profiles/default/cssregistry.xml
cs/video/profiles/default/factorytool.xml
cs/video/profiles/default/jsregistry.xml
cs/video/profiles/default/metadata.xml
cs/video/profiles/default/rolemap.xml
cs/video/profiles/default/skins.xml
cs/video/profiles/default/types.xml
cs/video/profiles/default/types/Folder.xml
cs/video/profiles/default/types/Video.xml
cs/video/skins/video_templates/all_videos.pt
cs/video/skins/video_templates/all_videos.pt.metadata
cs/video/skins/video_templates/cs-video.css
cs/video/skins/video_templates/flashembed.min.js
cs/video/skins/video_templates/flowplayer-3.2.10.swf
cs/video/skins/video_templates/flowplayer-3.2.9.min.js
cs/video/skins/video_templates/flowplayer.audio-3.1.2.swf
cs/video/skins/video_templates/flowplayer.controls-3.2.10.swf
cs/video/skins/video_templates/flowplayer.embed-3.0.3.min.js
cs/video/skins/video_templates/play.png
cs/video/skins/video_templates/video_archive.pt
cs/video/skins/video_templates/video_archive.pt.metadata
cs/video/skins/video_templates/video_icon.gif
cs/video/skins/video_templates/video_view.pt
