Metadata-Version: 2.1
Name: cs.video
Version: 3.1
Summary: Video object for referring external FLV files
Home-page: http://code.codesyntax.com/private/cs.video
Author: Mikel Larreategi
Author-email: mlarreategi@codesyntax.com
License: GPL
Platform: UNKNOWN
Classifier: Framework :: Plone
Classifier: Intended Audience :: Developers
Classifier: Topic :: Software Development :: Libraries :: Python Modules
Classifier: License :: OSI Approved :: GNU General Public License (GPL)
Provides-Extra: tests
